hipscat_import/__init__.py
hipscat_import/_version.py
hipscat_import/pipeline.py
hipscat_import/pipeline_resume_plan.py
hipscat_import/py.typed
hipscat_import/runtime_arguments.py
hipscat_import/catalog/__init__.py
hipscat_import/catalog/arguments.py
hipscat_import/catalog/file_readers.py
hipscat_import/catalog/map_reduce.py
hipscat_import/catalog/resume_plan.py
hipscat_import/catalog/run_import.py
hipscat_import/catalog/sparse_histogram.py
hipscat_import/index/__init__.py
hipscat_import/index/arguments.py
hipscat_import/index/map_reduce.py
hipscat_import/index/run_index.py
hipscat_import/margin_cache/__init__.py
hipscat_import/margin_cache/margin_cache.py
hipscat_import/margin_cache/margin_cache_arguments.py
hipscat_import/margin_cache/margin_cache_map_reduce.py
hipscat_import/margin_cache/margin_cache_resume_plan.py
hipscat_import/soap/__init__.py
hipscat_import/soap/arguments.py
hipscat_import/soap/map_reduce.py
hipscat_import/soap/resume_plan.py
hipscat_import/soap/run_soap.py
hipscat_import/verification/__init__.py
hipscat_import/verification/arguments.py
hipscat_import/verification/run_verification.py
hipscat_import-0.3.5.dist-info/LICENSE
hipscat_import-0.3.5.dist-info/METADATA
hipscat_import-0.3.5.dist-info/WHEEL
hipscat_import-0.3.5.dist-info/top_level.txt
hipscat_import-0.3.5.dist-info/RECORD
