Metadata-Version: 2.1
Name: hipscat-import
Version: 0.3.5
Author-email: LINCC Frameworks <lincc-frameworks-team@lists.lsst.org>
License: BSD 3-Clause License
Classifier: Development Status :: 4 - Beta
Classifier: License :: OSI Approved :: BSD License
Classifier: Intended Audience :: Developers
Classifier: Intended Audience :: Science/Research
Classifier: Operating System :: OS Independent
Classifier: Programming Language :: Python
License-File: LICENSE
Requires-Dist: dask[complete] >=2024.3.0
Requires-Dist: deprecated
Requires-Dist: hipscat >=0.3.8
Requires-Dist: ipykernel
Requires-Dist: numpy
Requires-Dist: pandas
Requires-Dist: pyarrow
Requires-Dist: pyyaml
Requires-Dist: scipy
Requires-Dist: tqdm
Provides-Extra: dev
Requires-Dist: black ; extra == 'dev'
Requires-Dist: jupyter ; extra == 'dev'
Requires-Dist: mypy ; extra == 'dev'
Requires-Dist: pre-commit ; extra == 'dev'
Requires-Dist: pylint ; extra == 'dev'
Requires-Dist: pytest ; extra == 'dev'
Requires-Dist: pytest-cov ; extra == 'dev'
Requires-Dist: pytest-timeout ; extra == 'dev'
Requires-Dist: ray ; extra == 'dev'
Requires-Dist: types-PyYAML ; extra == 'dev'
